<?xml version="1.0"?>
<!DOCTYPE hibernate-mapping PUBLIC "-//Hibernate/Hibernate Mapping DTD 3.0//EN"
"http://hibernate.sourceforge.net/hibernate-mapping-3.0.dtd">
<!-- Generated Nov 27, 2016 4:04:37 PM by Hibernate Tools 3.4.0.CR1 -->
<hibernate-mapping>
    <class name="ecommerceserver.post" table="POST">
        <id name="postid" type="int">
            <column name="POSTID" />
            <generator class="assigned" />
        </id>
        <property name="cid" type="int">
            <column name="CID" />
        </property>
        <property name="about" type="java.lang.String">
            <column name="ABOUT" />
        </property>
        <property name="postdesc" type="java.lang.String" access="field">
            <column name="POSTDESC" />
        </property>
        <property name="quantity" type="int">
            <column name="QUANTITY" />
        </property>
        <property name="price" type="float">
            <column name="PRICE" />
        </property>
        <property name="createdat" type="java.util.Date">
            <column name="CREATEDAT" />
        </property>
    </class>
</hibernate-mapping>
